owklx/__init__.py
owklx-0.1.0.dist-info/METADATA
owklx-0.1.0.dist-info/WHEEL
owklx-0.1.0.dist-info/top_level.txt
owklx-0.1.0.dist-info/RECORD
