Metadata-Version: 2.4
Name: owklx
Version: 0.1.0
Summary: le meilleur module de 2025 pour discord (bypass api, nouvelle bibliothèque...)
Home-page: https://github.com/owklx
Author: owklx
Author-email: cpascontent@proton.me
Classifier: Programming Language :: Python :: 3
Classifier: License :: OSI Approved :: MIT License
Requires-Python: >=3.6
Dynamic: author
Dynamic: author-email
Dynamic: classifier
Dynamic: description-content-type
Dynamic: home-page
Dynamic: requires-python
Dynamic: summary
